qiskit_qir/__init__.py
qiskit_qir/capability.py
qiskit_qir/elements.py
qiskit_qir/translate.py
qiskit_qir/visitor.py
qiskit_qir-0.5.0.dist-info/LICENSE
qiskit_qir-0.5.0.dist-info/METADATA
qiskit_qir-0.5.0.dist-info/NOTICE.txt
qiskit_qir-0.5.0.dist-info/WHEEL
qiskit_qir-0.5.0.dist-info/top_level.txt
qiskit_qir-0.5.0.dist-info/RECORD
